framelink/__init__.py
framelink/__main__.py
framelink/__version__.py
framelink/_cli.py
framelink/_util.py
framelink/core.py
framelink/types.py
framelink/storage/__init__.py
framelink/storage/core.py
framelink/storage/interfaces.py
framelink-0.2.2.dist-info/METADATA
framelink-0.2.2.dist-info/WHEEL
framelink-0.2.2.dist-info/entry_points.txt
framelink-0.2.2.dist-info/top_level.txt
framelink-0.2.2.dist-info/RECORD
