Metadata-Version: 2.1
Name: framelink
Version: 0.2.2
Author-email: Toby Devlin <toby@tobydevlin.com>
Project-URL: github, https://github.com/GitToby/framelink
Keywords: data,DAG,orchastration,dataframe
Classifier: Development Status :: 4 - Beta
Requires-Python: <4.0,>=3.8
Requires-Dist: networkx (>=3.0)
Requires-Dist: typer[all] (>=0.7.0)
Provides-Extra: dev
Requires-Dist: framelink ; extra == 'dev'
Requires-Dist: framelink[viz] ; extra == 'dev'
Requires-Dist: openlineage-python (>=0.21.1) ; extra == 'dev'
Requires-Dist: setuptools-scm (>=7.1.0) ; extra == 'dev'
Requires-Dist: pytest (>=7.2.2) ; extra == 'dev'
Requires-Dist: pytest-cov (>=4.0.0) ; extra == 'dev'
Requires-Dist: mypy (>=1.1.1) ; extra == 'dev'
Requires-Dist: ruff (>=0.0.258) ; extra == 'dev'
Requires-Dist: black (>=23.1.0) ; extra == 'dev'
Requires-Dist: build (>=0.10.0) ; extra == 'dev'
Requires-Dist: pandas (<2.0.0,>=1.5.3) ; extra == 'dev'
Requires-Dist: polars (<1.0.0,>=0.16.7) ; extra == 'dev'
Requires-Dist: pre-commit (>=3.2.0) ; extra == 'dev'
Requires-Dist: pyment (>=0.3.3) ; extra == 'dev'
Requires-Dist: pyarrow (>=11.0.0) ; extra == 'dev'
Requires-Dist: jupyter (>=1.0.0) ; extra == 'dev'
Provides-Extra: viz
Requires-Dist: matplotlib (>=3.7.1) ; extra == 'viz'
Requires-Dist: graphviz (>=0.20.1) ; extra == 'viz'
Requires-Dist: pydot (>=1.4.2) ; extra == 'viz'
